{
  "directory_items": [
    {
      "id": 466,
      "solutions": 0,
      "gamification_score": 5,
      "likes_received": 0,
      "likes_given": 0,
      "topic_count": 1,
      "post_count": 1,
      "topics_entered": 33,
      "posts_read": 115,
      "days_visited": 18,
      "time_read": 3065,
      "user": {
        "id": 466,
        "username": "Shreyans",
        "name": "Shreyans Jain",
        "avatar_template": "/user_avatar/discourse.onlinedegree.iitm.ac.in/shreyans/{size}/41449_2.png",
        "title": null,
        "primary_group_name": "ds-students",
        "flair_name": "ds-students",
        "flair_group_id": 294,
        "trust_level": 0
      }
    },
    {
      "id": 467,
      "solutions": 0,
      "gamification_score": 3,
      "likes_received": 1,
      "likes_given": 1,
      "topic_count": 0,
      "post_count": 1,
      "topics_entered": 12,
      "posts_read": 38,
      "days_visited": 21,
      "time_read": 1076,
      "user": {
        "id": 467,
        "username": "ykl_ds.iitm",
        "name": "YASH LOHANA",
        "avatar_template": "/user_avatar/discourse.onlinedegree.iitm.ac.in/ykl_ds.iitm/{size}/88_2.png",
        "title": null,
        "primary_group_name": "ds-students",
        "flair_name": "ds-students",
        "flair_group_id": 294,
        "trust_level": 0
      }
    },
    {
      "id": 468,
      "solutions": 0,
      "gamification_score": 334,
      "likes_received": 66,
      "likes_given": 179,
      "topic_count": 7,
      "post_count": 118,
      "topics_entered": 751,
      "posts_read": 5591,
      "days_visited": 206,
      "time_read": 80275,
      "user": {
        "id": 468,
        "username": "ajeet",
        "name": "Ajeet kumar",
        "avatar_template": "/user_avatar/discourse.onlinedegree.iitm.ac.in/ajeet/{size}/14725_2.png",
        "title": null,
        "primary_group_name": "ds-students",
        "flair_name": "ds-students",
        "flair_group_id": 294,
        "trust_level": 1
      }
    },
    {
      "id": 469,
      "solutions": 0,
      "gamification_score": 0,
      "likes_received": 0,
      "likes_given": 0,
      "topic_count": 0,
      "post_count": 0,
      "topics_entered": 4,
      "posts_read": 33,
      "days_visited": 3,
      "time_read": 487,
      "user": {
        "id": 469,
        "username": "FABRO",
        "name": "DEVA NANDH V",
        "avatar_template": "/user_avatar/discourse.onlinedegree.iitm.ac.in/fabro/{size}/28209_2.png",
        "title": null,
        "primary_group_name": "ds-students",
        "flair_name": "ds-students",
        "flair_group_id": 294,
        "trust_level": 0
      }
    },
    {
      "id": 470,
      "solutions": 0,
      "gamification_score": 158,
      "likes_received": 1,
      "likes_given": 2,
      "topic_count": 2,
      "post_count": 21,
      "topics_entered": 167,
      "posts_read": 940,
      "days_visited": 115,
      "time_read": 19445,
      "user": {
        "id": 470,
        "username": "SAV",
        "name": "Abishek Vinodh ",
        "avatar_template": "/user_avatar/discourse.onlinedegree.iitm.ac.in/sav/{size}/328_2.png",
        "title": "",
        "primary_group_name": "ds-students",
        "flair_name": "ds-students",
        "flair_group_id": 294,
        "trust_level": 1
      }
    },
    {
      "id": 471,
      "solutions": 7,
      "gamification_score": 618,
      "likes_received": 97,
      "likes_given": 68,
      "topic_count": 48,
      "post_count": 227,
      "topics_entered": 1099,
      "posts_read": 5660,
      "days_visited": 411,
      "time_read": 147966,
      "user": {
        "id": 471,
        "username": "ViroopakshC",
        "name": "BlackMoonBear",
        "avatar_template": "/user_avatar/discourse.onlinedegree.iitm.ac.in/viroopakshc/{size}/9962_2.png",
        "title": "",
        "primary_group_name": "ds-students",
        "flair_name": "ds-students",
        "flair_group_id": 294,
        "trust_level": 1
      }
    },
    {
      "id": 472,
      "solutions": 1,
      "gamification_score": 308,
      "likes_received": 15,
      "likes_given": 43,
      "topic_count": 13,
      "post_count": 48,
      "topics_entered": 645,
      "posts_read": 3668,
      "days_visited": 234,
      "time_read": 56205,
      "user": {
        "id": 472,
        "username": "21f1001712",
        "name": "Rohit Kumar",
        "avatar_template": "/user_avatar/discourse.onlinedegree.iitm.ac.in/21f1001712/{size}/619_2.png",
        "title": "",
        "primary_group_name": "ds-students",
        "flair_name": "ds-students",
        "flair_group_id": 294,
        "trust_level": 1
      }
    },
    {
      "id": 473,
      "solutions": 0,
      "gamification_score": 0,
      "likes_received": 0,
      "likes_given": 1,
      "topic_count": 0,
      "post_count": 0,
      "topics_entered": 180,
      "posts_read": 1127,
      "days_visited": 73,
      "time_read": 17332,
      "user": {
        "id": 473,
        "username": "sajan",
        "name": "sajjan louie",
        "avatar_template": "/user_avatar/discourse.onlinedegree.iitm.ac.in/sajan/{size}/116_2.png",
        "title": null,
        "primary_group_name": "ds-students",
        "flair_name": "ds-students",
        "flair_group_id": 294,
        "trust_level": 1
      }
    },
    {
      "id": 474,
      "solutions": 1,
      "gamification_score": 269,
      "likes_received": 6,
      "likes_given": 29,
      "topic_count": 5,
      "post_count": 6,
      "topics_entered": 355,
      "posts_read": 1511,
      "days_visited": 245,
      "time_read": 24393,
      "user": {
        "id": 474,
        "username": "Vasista_Dev",
        "name": "Deva Vasista",
        "avatar_template": "/user_avatar/discourse.onlinedegree.iitm.ac.in/vasista_dev/{size}/12430_2.png",
        "title": null,
        "primary_group_name": "ds-students",
        "flair_name": "ds-students",
        "flair_group_id": 294,
        "trust_level": 1
      }
    },
    {
      "id": 476,
      "solutions": 0,
      "gamification_score": 42,
      "likes_received": 2,
      "likes_given": 4,
      "topic_count": 3,
      "post_count": 6,
      "topics_entered": 262,
      "posts_read": 1324,
      "days_visited": 112,
      "time_read": 16538,
      "user": {
        "id": 476,
        "username": "sri",
        "name": "Sriharan",
        "avatar_template": "/user_avatar/discourse.onlinedegree.iitm.ac.in/sri/{size}/210_2.png",
        "title": null,
        "primary_group_name": "ds-students",
        "flair_name": "ds-students",
        "flair_group_id": 294,
        "trust_level": 1
      }
    },
    {
      "id": 477,
      "solutions": 0,
      "gamification_score": 17,
      "likes_received": 0,
      "likes_given": 1,
      "topic_count": 0,
      "post_count": 1,
      "topics_entered": 132,
      "posts_read": 815,
      "days_visited": 51,
      "time_read": 8974,
      "user": {
        "id": 477,
        "username": "Ibrahim",
        "name": "Mohammed Ibrahim",
        "avatar_template": "/user_avatar/discourse.onlinedegree.iitm.ac.in/ibrahim/{size}/828_2.png",
        "title": null,
        "primary_group_name": "ds-students",
        "flair_name": "ds-students",
        "flair_group_id": 294,
        "trust_level": 1
      }
    },
    {
      "id": 478,
      "solutions": 1,
      "gamification_score": 213,
      "likes_received": 13,
      "likes_given": 2,
      "topic_count": 2,
      "post_count": 35,
      "topics_entered": 152,
      "posts_read": 1540,
      "days_visited": 119,
      "time_read": 25861,
      "user": {
        "id": 478,
        "username": "Surya1113",
        "name": "Sivasurya E. ",
        "avatar_template": "/user_avatar/discourse.onlinedegree.iitm.ac.in/surya1113/{size}/1278_2.png",
        "title": null,
        "primary_group_name": "ds-students",
        "flair_name": "ds-students",
        "flair_group_id": 294,
        "trust_level": 1
      }
    },
    {
      "id": 480,
      "solutions": 0,
      "gamification_score": 60,
      "likes_received": 5,
      "likes_given": 14,
      "topic_count": 4,
      "post_count": 13,
      "topics_entered": 562,
      "posts_read": 2892,
      "days_visited": 185,
      "time_read": 77757,
      "user": {
        "id": 480,
        "username": "Vikashkumar",
        "name": "Vikash kumar",
        "avatar_template": "/user_avatar/discourse.onlinedegree.iitm.ac.in/vikashkumar/{size}/77_2.png",
        "title": null,
        "primary_group_name": "ds-students",
        "flair_name": "ds-students",
        "flair_group_id": 294,
        "trust_level": 1
      }
    },
    {
      "id": 481,
      "solutions": 0,
      "gamification_score": 16,
      "likes_received": 0,
      "likes_given": 0,
      "topic_count": 0,
      "post_count": 0,
      "topics_entered": 95,
      "posts_read": 442,
      "days_visited": 30,
      "time_read": 6632,
      "user": {
        "id": 481,
        "username": "Sangi",
        "name": "Sandra Mary Jacob",
        "avatar_template": "/user_avatar/discourse.onlinedegree.iitm.ac.in/sangi/{size}/127_2.png",
        "title": null,
        "primary_group_name": "ds-students",
        "flair_name": "ds-students",
        "flair_group_id": 294,
        "trust_level": 1
      }
    },
    {
      "id": 482,
      "solutions": 0,
      "gamification_score": 159,
      "likes_received": 3,
      "likes_given": 7,
      "topic_count": 1,
      "post_count": 5,
      "topics_entered": 444,
      "posts_read": 2194,
      "days_visited": 215,
      "time_read": 35009,
      "user": {
        "id": 482,
        "username": "nks",
        "name": "Naveen Kumar Saini",
        "avatar_template": "/user_avatar/discourse.onlinedegree.iitm.ac.in/nks/{size}/1039_2.png",
        "title": "",
        "primary_group_name": "ds-students",
        "flair_name": "ds-students",
        "flair_group_id": 294,
        "trust_level": 1
      }
    },
    {
      "id": 483,
      "solutions": 1,
      "gamification_score": 702,
      "likes_received": 103,
      "likes_given": 495,
      "topic_count": 359,
      "post_count": 381,
      "topics_entered": 2011,
      "posts_read": 9175,
      "days_visited": 446,
      "time_read": 232356,
      "user": {
        "id": 483,
        "username": "Mehak",
        "name": "Mehak",
        "avatar_template": "/user_avatar/discourse.onlinedegree.iitm.ac.in/mehak/{size}/634_2.png",
        "title": null,
        "primary_group_name": "ds-students",
        "flair_name": "ds-students",
        "flair_group_id": 294,
        "trust_level": 1
      }
    },
    {
      "id": 484,
      "solutions": 0,
      "gamification_score": 114,
      "likes_received": 5,
      "likes_given": 2,
      "topic_count": 7,
      "post_count": 22,
      "topics_entered": 86,
      "posts_read": 1074,
      "days_visited": 83,
      "time_read": 14810,
      "user": {
        "id": 484,
        "username": "Architgarg03",
        "name": "Archit Garg",
        "avatar_template": "/user_avatar/discourse.onlinedegree.iitm.ac.in/architgarg03/{size}/213_2.png",
        "title": null,
        "primary_group_name": "ds-students",
        "flair_name": "ds-students",
        "flair_group_id": 294,
        "trust_level": 1
      }
    },
    {
      "id": 485,
      "solutions": 15,
      "gamification_score": 550,
      "likes_received": 460,
      "likes_given": 198,
      "topic_count": 67,
      "post_count": 346,
      "topics_entered": 1934,
      "posts_read": 10100,
      "days_visited": 629,
      "time_read": 430902,
      "user": {
        "id": 485,
        "username": "Kumar9",
        "name": "kumar",
        "avatar_template": "/user_avatar/discourse.onlinedegree.iitm.ac.in/kumar9/{size}/14_2.png",
        "title": "",
        "primary_group_name": "ds-students",
        "flair_name": "ds-students",
        "flair_group_id": 294,
        "trust_level": 1
      }
    },
    {
      "id": 486,
      "solutions": 0,
      "gamification_score": 0,
      "likes_received": 0,
      "likes_given": 0,
      "topic_count": 0,
      "post_count": 5,
      "topics_entered": 22,
      "posts_read": 210,
      "days_visited": 14,
      "time_read": 3724,
      "user": {
        "id": 486,
        "username": "Indu",
        "name": "Indulekshmi",
        "avatar_template": "/user_avatar/discourse.onlinedegree.iitm.ac.in/indu/{size}/424_2.png",
        "title": null,
        "primary_group_name": "ds-students",
        "flair_name": "ds-students",
        "flair_group_id": 294,
        "trust_level": 0
      }
    },
    {
      "id": 487,
      "solutions": 0,
      "gamification_score": 5,
      "likes_received": 0,
      "likes_given": 1,
      "topic_count": 0,
      "post_count": 0,
      "topics_entered": 28,
      "posts_read": 235,
      "days_visited": 32,
      "time_read": 4052,
      "user": {
        "id": 487,
        "username": "Sahilpreet",
        "name": "Sahilpreet Singh",
        "avatar_template": "/user_avatar/discourse.onlinedegree.iitm.ac.in/sahilpreet/{size}/84_2.png",
        "title": null,
        "primary_group_name": "ds-students",
        "flair_name": "ds-students",
        "flair_group_id": 294,
        "trust_level": 0
      }
    },
    {
      "id": 488,
      "solutions": 0,
      "gamification_score": 46,
      "likes_received": 2,
      "likes_given": 7,
      "topic_count": 5,
      "post_count": 7,
      "topics_entered": 142,
      "posts_read": 683,
      "days_visited": 38,
      "time_read": 8824,
      "user": {
        "id": 488,
        "username": "himanshu",
        "name": "Himanshu Agarwal",
        "avatar_template": "/user_avatar/discourse.onlinedegree.iitm.ac.in/himanshu/{size}/5338_2.png",
        "title": null,
        "primary_group_name": "ds-students",
        "flair_name": "ds-students",
        "flair_group_id": 294,
        "trust_level": 1
      }
    },
    {
      "id": 489,
      "solutions": 0,
      "gamification_score": 201,
      "likes_received": 22,
      "likes_given": 24,
      "topic_count": 6,
      "post_count": 71,
      "topics_entered": 237,
      "posts_read": 1883,
      "days_visited": 117,
      "time_read": 34600,
      "user": {
        "id": 489,
        "username": "Prem",
        "name": "Prem Kumar",
        "avatar_template": "/user_avatar/discourse.onlinedegree.iitm.ac.in/prem/{size}/90473_2.png",
        "title": null,
        "primary_group_name": "ds-students",
        "flair_name": "ds-students",
        "flair_group_id": 294,
        "trust_level": 1
      }
    },
    {
      "id": 490,
      "solutions": 1,
      "gamification_score": 221,
      "likes_received": 14,
      "likes_given": 31,
      "topic_count": 6,
      "post_count": 25,
      "topics_entered": 725,
      "posts_read": 3811,
      "days_visited": 384,
      "time_read": 71309,
      "user": {
        "id": 490,
        "username": "abhinavudupi",
        "name": "Abhinav Udupi",
        "avatar_template": "/user_avatar/discourse.onlinedegree.iitm.ac.in/abhinavudupi/{size}/12485_2.png",
        "title": null,
        "primary_group_name": "ds-students",
        "flair_name": "ds-students",
        "flair_group_id": 294,
        "trust_level": 1
      }
    },
    {
      "id": 492,
      "solutions": 0,
      "gamification_score": 264,
      "likes_received": 10,
      "likes_given": 184,
      "topic_count": 23,
      "post_count": 56,
      "topics_entered": 862,
      "posts_read": 4852,
      "days_visited": 226,
      "time_read": 85701,
      "user": {
        "id": 492,
        "username": "21f1004370",
        "name": "Meera Jose ",
        "avatar_template": "/user_avatar/discourse.onlinedegree.iitm.ac.in/21f1004370/{size}/151_2.png",
        "title": null,
        "primary_group_name": "ds-students",
        "flair_name": "ds-students",
        "flair_group_id": 294,
        "trust_level": 1
      }
    },
    {
      "id": 494,
      "solutions": 0,
      "gamification_score": 6,
      "likes_received": 2,
      "likes_given": 0,
      "topic_count": 7,
      "post_count": 10,
      "topics_entered": 59,
      "posts_read": 280,
      "days_visited": 27,
      "time_read": 8651,
      "user": {
        "id": 494,
        "username": "Kunwarsingh",
        "name": "KUNWAR SINGH",
        "avatar_template": "/user_avatar/discourse.onlinedegree.iitm.ac.in/kunwarsingh/{size}/92_2.png",
        "title": null,
        "primary_group_name": "ds-students",
        "flair_name": "ds-students",
        "flair_group_id": 294,
        "trust_level": 1
      }
    },
    {
      "id": 495,
      "solutions": 0,
      "gamification_score": 0,
      "likes_received": 0,
      "likes_given": 0,
      "topic_count": 0,
      "post_count": 0,
      "topics_entered": 24,
      "posts_read": 148,
      "days_visited": 10,
      "time_read": 1170,
      "user": {
        "id": 495,
        "username": "VBChaitanya",
        "name": "VBChaitanya",
        "avatar_template": "/user_avatar/discourse.onlinedegree.iitm.ac.in/vbchaitanya/{size}/12651_2.png",
        "title": null,
        "primary_group_name": "ds-students",
        "flair_name": "ds-students",
        "flair_group_id": 294,
        "trust_level": 0
      }
    },
    {
      "id": 496,
      "solutions": 0,
      "gamification_score": 103,
      "likes_received": 7,
      "likes_given": 10,
      "topic_count": 13,
      "post_count": 11,
      "topics_entered": 143,
      "posts_read": 769,
      "days_visited": 73,
      "time_read": 11873,
      "user": {
        "id": 496,
        "username": "VISHAL_YADAV",
        "name": "VISHAL YADAV",
        "avatar_template": "/user_avatar/discourse.onlinedegree.iitm.ac.in/vishal_yadav/{size}/93_2.png",
        "title": null,
        "primary_group_name": "ds-students",
        "flair_name": "ds-students",
        "flair_group_id": 294,
        "trust_level": 1
      }
    },
    {
      "id": 497,
      "solutions": 3,
      "gamification_score": 173,
      "likes_received": 17,
      "likes_given": 23,
      "topic_count": 8,
      "post_count": 40,
      "topics_entered": 372,
      "posts_read": 1832,
      "days_visited": 246,
      "time_read": 55682,
      "user": {
        "id": 497,
        "username": "ravinaithani",
        "name": "Ravindra Naithani",
        "avatar_template": "/user_avatar/discourse.onlinedegree.iitm.ac.in/ravinaithani/{size}/847_2.png",
        "title": null,
        "primary_group_name": "ds-students",
        "flair_name": "ds-students",
        "flair_group_id": 294,
        "trust_level": 1
      }
    },
    {
      "id": 498,
      "solutions": 0,
      "gamification_score": 88,
      "likes_received": 4,
      "likes_given": 0,
      "topic_count": 0,
      "post_count": 20,
      "topics_entered": 332,
      "posts_read": 2526,
      "days_visited": 84,
      "time_read": 23998,
      "user": {
        "id": 498,
        "username": "Shamel",
        "name": "Shamel Fahd",
        "avatar_template": "/user_avatar/discourse.onlinedegree.iitm.ac.in/shamel/{size}/13822_2.png",
        "title": null,
        "primary_group_name": "ds-students",
        "flair_name": "ds-students",
        "flair_group_id": 294,
        "trust_level": 1
      }
    },
    {
      "id": 499,
      "solutions": 0,
      "gamification_score": 22,
      "likes_received": 2,
      "likes_given": 6,
      "topic_count": 1,
      "post_count": 8,
      "topics_entered": 143,
      "posts_read": 919,
      "days_visited": 39,
      "time_read": 12598,
      "user": {
        "id": 499,
        "username": "rajeshy45",
        "name": "Rajesh Yemineni",
        "avatar_template": "/user_avatar/discourse.onlinedegree.iitm.ac.in/rajeshy45/{size}/22605_2.png",
        "title": null,
        "primary_group_name": "ds-students",
        "flair_name": "ds-students",
        "flair_group_id": 294,
        "trust_level": 1
      }
    },
    {
      "id": 500,
      "solutions": 0,
      "gamification_score": 0,
      "likes_received": 0,
      "likes_given": 0,
      "topic_count": 0,
      "post_count": 0,
      "topics_entered": 10,
      "posts_read": 43,
      "days_visited": 4,
      "time_read": 336,
      "user": {
        "id": 500,
        "username": "SouravSinha",
        "name": "Sourav Sinha",
        "avatar_template": "/user_avatar/discourse.onlinedegree.iitm.ac.in/souravsinha/{size}/9293_2.png",
        "title": null,
        "primary_group_name": "ds-students",
        "flair_name": "ds-students",
        "flair_group_id": 294,
        "trust_level": 0
      }
    },
    {
      "id": 501,
      "solutions": 0,
      "gamification_score": 34,
      "likes_received": 5,
      "likes_given": 0,
      "topic_count": 5,
      "post_count": 7,
      "topics_entered": 185,
      "posts_read": 707,
      "days_visited": 57,
      "time_read": 17259,
      "user": {
        "id": 501,
        "username": "Haarini",
        "name": "21f1007051",
        "avatar_template": "https://avatars.discourse-cdn.com/v4/letter/h/7c8e57/{size}.png",
        "title": "",
        "primary_group_name": "ds-students",
        "flair_name": "ds-students",
        "flair_group_id": 294,
        "trust_level": 1
      }
    },
    {
      "id": 503,
      "solutions": 0,
      "gamification_score": 322,
      "likes_received": 8,
      "likes_given": 26,
      "topic_count": 9,
      "post_count": 44,
      "topics_entered": 532,
      "posts_read": 3375,
      "days_visited": 319,
      "time_read": 82860,
      "user": {
        "id": 503,
        "username": "mehtashish778",
        "name": "Ashish Mehta",
        "avatar_template": "/user_avatar/discourse.onlinedegree.iitm.ac.in/mehtashish778/{size}/12653_2.png",
        "title": "",
        "primary_group_name": "ds-students",
        "flair_name": "ds-students",
        "flair_group_id": 294,
        "trust_level": 1
      }
    },
    {
      "id": 504,
      "solutions": 0,
      "gamification_score": 2,
      "likes_received": 5,
      "likes_given": 15,
      "topic_count": 0,
      "post_count": 7,
      "topics_entered": 870,
      "posts_read": 3156,
      "days_visited": 230,
      "time_read": 49902,
      "user": {
        "id": 504,
        "username": "Soumitri",
        "name": "Soumitri",
        "avatar_template": "/user_avatar/discourse.onlinedegree.iitm.ac.in/soumitri/{size}/12682_2.png",
        "title": null,
        "primary_group_name": "ds-students",
        "flair_name": "ds-students",
        "flair_group_id": 294,
        "trust_level": 1
      }
    },
    {
      "id": 506,
      "solutions": 0,
      "gamification_score": 97,
      "likes_received": 18,
      "likes_given": 23,
      "topic_count": 1,
      "post_count": 29,
      "topics_entered": 443,
      "posts_read": 2791,
      "days_visited": 135,
      "time_read": 40971,
      "user": {
        "id": 506,
        "username": "Shikhar2807",
        "name": "Akshay Shikhar Srivastava",
        "avatar_template": "/user_avatar/discourse.onlinedegree.iitm.ac.in/shikhar2807/{size}/655_2.png",
        "title": "",
        "primary_group_name": "ds-students",
        "flair_name": "ds-students",
        "flair_group_id": 294,
        "trust_level": 1
      }
    },
    {
      "id": 507,
      "solutions": 0,
      "gamification_score": 323,
      "likes_received": 6,
      "likes_given": 4,
      "topic_count": 0,
      "post_count": 13,
      "topics_entered": 691,
      "posts_read": 4194,
      "days_visited": 279,
      "time_read": 58747,
      "user": {
        "id": 507,
        "username": "Schwartz",
        "name": "Schwartz Rajadurai",
        "avatar_template": "/user_avatar/discourse.onlinedegree.iitm.ac.in/schwartz/{size}/127_2.png",
        "title": null,
        "primary_group_name": "ds-students",
        "flair_name": "ds-students",
        "flair_group_id": 294,
        "trust_level": 1
      }
    },
    {
      "id": 508,
      "solutions": 0,
      "gamification_score": 2,
      "likes_received": 0,
      "likes_given": 6,
      "topic_count": 0,
      "post_count": 0,
      "topics_entered": 39,
      "posts_read": 467,
      "days_visited": 32,
      "time_read": 7774,
      "user": {
        "id": 508,
        "username": "RavinderSinghPB",
        "name": "Ravinder Singh",
        "avatar_template": "/user_avatar/discourse.onlinedegree.iitm.ac.in/ravindersinghpb/{size}/392_2.png",
        "title": null,
        "primary_group_name": "ds-students",
        "flair_name": "ds-students",
        "flair_group_id": 294,
        "trust_level": 1
      }
    },
    {
      "id": 509,
      "solutions": 0,
      "gamification_score": 2,
      "likes_received": 0,
      "likes_given": 0,
      "topic_count": 0,
      "post_count": 0,
      "topics_entered": 7,
      "posts_read": 24,
      "days_visited": 13,
      "time_read": 596,
      "user": {
        "id": 509,
        "username": "Ananthu",
        "name": "Anantha Padmanabhan A",
        "avatar_template": "/user_avatar/discourse.onlinedegree.iitm.ac.in/ananthu/{size}/295_2.png",
        "title": null,
        "primary_group_name": "ds-students",
        "flair_name": "ds-students",
        "flair_group_id": 294,
        "trust_level": 0
      }
    },
    {
      "id": 510,
      "solutions": 1,
      "gamification_score": 443,
      "likes_received": 17,
      "likes_given": 89,
      "topic_count": 35,
      "post_count": 52,
      "topics_entered": 656,
      "posts_read": 3009,
      "days_visited": 202,
      "time_read": 61457,
      "user": {
        "id": 510,
        "username": "ankit2001",
        "name": "Ankit Kumar",
        "avatar_template": "/user_avatar/discourse.onlinedegree.iitm.ac.in/ankit2001/{size}/332_2.png",
        "title": null,
        "primary_group_name": "ds-students",
        "flair_name": "ds-students",
        "flair_group_id": 294,
        "trust_level": 1
      }
    },
    {
      "id": 511,
      "solutions": 0,
      "gamification_score": 2,
      "likes_received": 0,
      "likes_given": 2,
      "topic_count": 1,
      "post_count": 3,
      "topics_entered": 34,
      "posts_read": 158,
      "days_visited": 14,
      "time_read": 3234,
      "user": {
        "id": 511,
        "username": "Shael",
        "name": "Shailza Bansal",
        "avatar_template": "/user_avatar/discourse.onlinedegree.iitm.ac.in/shael/{size}/12589_2.png",
        "title": null,
        "primary_group_name": "ds-students",
        "flair_name": "ds-students",
        "flair_group_id": 294,
        "trust_level": 0
      }
    },
    {
      "id": 512,
      "solutions": 0,
      "gamification_score": 78,
      "likes_received": 0,
      "likes_given": 1,
      "topic_count": 0,
      "post_count": 4,
      "topics_entered": 252,
      "posts_read": 1568,
      "days_visited": 93,
      "time_read": 24904,
      "user": {
        "id": 512,
        "username": "TEELLA_BHANU",
        "name": "TEELLA BHANU",
        "avatar_template": "/user_avatar/discourse.onlinedegree.iitm.ac.in/teella_bhanu/{size}/104_2.png",
        "title": null,
        "primary_group_name": "ds-students",
        "flair_name": "ds-students",
        "flair_group_id": 294,
        "trust_level": 1
      }
    },
    {
      "id": 513,
      "solutions": 15,
      "gamification_score": 515,
      "likes_received": 114,
      "likes_given": 260,
      "topic_count": 30,
      "post_count": 170,
      "topics_entered": 1567,
      "posts_read": 8637,
      "days_visited": 384,
      "time_read": 130984,
      "user": {
        "id": 513,
        "username": "Yash_k",
        "name": "Yash Gambhir",
        "avatar_template": "/user_avatar/discourse.onlinedegree.iitm.ac.in/yash_k/{size}/1052_2.png",
        "title": "",
        "primary_group_name": "ds-students",
        "flair_name": "ds-students",
        "flair_group_id": 294,
        "trust_level": 1
      }
    },
    {
      "id": 514,
      "solutions": 0,
      "gamification_score": 127,
      "likes_received": 7,
      "likes_given": 6,
      "topic_count": 4,
      "post_count": 12,
      "topics_entered": 412,
      "posts_read": 2015,
      "days_visited": 143,
      "time_read": 34316,
      "user": {
        "id": 514,
        "username": "Satya",
        "name": "Satyabrata Dwivedy",
        "avatar_template": "/user_avatar/discourse.onlinedegree.iitm.ac.in/satya/{size}/13957_2.png",
        "title": "",
        "primary_group_name": "ds-students",
        "flair_name": "ds-students",
        "flair_group_id": 294,
        "trust_level": 1
      }
    },
    {
      "id": 515,
      "solutions": 0,
      "gamification_score": 121,
      "likes_received": 0,
      "likes_given": 2,
      "topic_count": 0,
      "post_count": 13,
      "topics_entered": 360,
      "posts_read": 3595,
      "days_visited": 103,
      "time_read": 54138,
      "user": {
        "id": 515,
        "username": "gouthamnischay",
        "name": "Chinnam Goutham Nischay",
        "avatar_template": "/user_avatar/discourse.onlinedegree.iitm.ac.in/gouthamnischay/{size}/255_2.png",
        "title": null,
        "primary_group_name": "ds-students",
        "flair_name": "ds-students",
        "flair_group_id": 294,
        "trust_level": 1
      }
    },
    {
      "id": 516,
      "solutions": 0,
      "gamification_score": 0,
      "likes_received": 0,
      "likes_given": 1,
      "topic_count": 0,
      "post_count": 2,
      "topics_entered": 16,
      "posts_read": 82,
      "days_visited": 23,
      "time_read": 1866,
      "user": {
        "id": 516,
        "username": "ashok",
        "name": "Ashok",
        "avatar_template": "/user_avatar/discourse.onlinedegree.iitm.ac.in/ashok/{size}/518_2.png",
        "title": null,
        "primary_group_name": "ds-students",
        "flair_name": "ds-students",
        "flair_group_id": 294,
        "trust_level": 0
      }
    },
    {
      "id": 517,
      "solutions": 0,
      "gamification_score": 1,
      "likes_received": 2,
      "likes_given": 1,
      "topic_count": 0,
      "post_count": 1,
      "topics_entered": 85,
      "posts_read": 530,
      "days_visited": 39,
      "time_read": 5421,
      "user": {
        "id": 517,
        "username": "harsh_raj",
        "name": "Harsh raj",
        "avatar_template": "/user_avatar/discourse.onlinedegree.iitm.ac.in/harsh_raj/{size}/607_2.png",
        "title": null,
        "primary_group_name": "ds-students",
        "flair_name": "ds-students",
        "flair_group_id": 294,
        "trust_level": 1
      }
    },
    {
      "id": 518,
      "solutions": 0,
      "gamification_score": 0,
      "likes_received": 0,
      "likes_given": 0,
      "topic_count": 0,
      "post_count": 0,
      "topics_entered": 7,
      "posts_read": 27,
      "days_visited": 7,
      "time_read": 274,
      "user": {
        "id": 518,
        "username": "swagata",
        "name": "SWAGATA SARKAR",
        "avatar_template": "/user_avatar/discourse.onlinedegree.iitm.ac.in/swagata/{size}/45_2.png",
        "title": null,
        "primary_group_name": "ds-students",
        "flair_name": "ds-students",
        "flair_group_id": 294,
        "trust_level": 0
      }
    },
    {
      "id": 519,
      "solutions": 0,
      "gamification_score": 5,
      "likes_received": 0,
      "likes_given": 0,
      "topic_count": 0,
      "post_count": 0,
      "topics_entered": 4,
      "posts_read": 22,
      "days_visited": 12,
      "time_read": 326,
      "user": {
        "id": 519,
        "username": "Osama",
        "name": "Osama Bin Aftab",
        "avatar_template": "/user_avatar/discourse.onlinedegree.iitm.ac.in/osama/{size}/7280_2.png",
        "title": null,
        "primary_group_name": "ds-students",
        "flair_name": "ds-students",
        "flair_group_id": 294,
        "trust_level": 0
      }
    },
    {
      "id": 520,
      "solutions": 0,
      "gamification_score": 82,
      "likes_received": 9,
      "likes_given": 0,
      "topic_count": 5,
      "post_count": 35,
      "topics_entered": 295,
      "posts_read": 1691,
      "days_visited": 94,
      "time_read": 24751,
      "user": {
        "id": 520,
        "username": "nithish0504",
        "name": "Arram Nithish",
        "avatar_template": "/user_avatar/discourse.onlinedegree.iitm.ac.in/nithish0504/{size}/182_2.png",
        "title": null,
        "primary_group_name": "ds-students",
        "flair_name": "ds-students",
        "flair_group_id": 294,
        "trust_level": 1
      }
    },
    {
      "id": 522,
      "solutions": 0,
      "gamification_score": 133,
      "likes_received": 1,
      "likes_given": 0,
      "topic_count": 0,
      "post_count": 2,
      "topics_entered": 905,
      "posts_read": 4467,
      "days_visited": 152,
      "time_read": 83637,
      "user": {
        "id": 522,
        "username": "Reshmi",
        "name": "Reshmi",
        "avatar_template": "/user_avatar/discourse.onlinedegree.iitm.ac.in/reshmi/{size}/267_2.png",
        "title": null,
        "primary_group_name": "ds-students",
        "flair_name": "ds-students",
        "flair_group_id": 294,
        "trust_level": 1
      }
    }
  ],
  "meta": {
    "last_updated_at": "2026-02-23T02:55:20.000Z",
    "total_rows_directory_items": 54163,
    "load_more_directory_items": "/directory_items.json?order=likes_recieved&page=9&period=all"
  }
}